setup.cfg
setup.py
test/test_comments.py
test/test_oauth.py
test/test_persons.py
test/test_playlists.py
test/test_schemas.py
test/test_searches.py
test/test_shows.py
test/test_upload.py
test/test_users.py
test/test_videos.py
youku/__init__.py
youku/util.py
youku/youku_comments.py
youku/youku_oauth.py
youku/youku_persons.py
youku/youku_playlists.py
youku/youku_schemas.py
youku/youku_searches.py
youku/youku_shows.py
youku/youku_upload.py
youku/youku_users.py
youku/youku_videos.py
youku.egg-info/PKG-INFO
youku.egg-info/SOURCES.txt
youku.egg-info/dependency_links.txt
youku.egg-info/requires.txt
youku.egg-info/top_level.txt