Metadata-Version: 1.1
Name: youku
Version: 0.0.7
Summary: Youku open api python client and video uploader
Home-page: https://github.com/hanguokai/youku
Author: Guokai Han
Author-email: han.guokai@gmail.com
License: UNKNOWN
Keywords: youku api upload video
Platform: UNKNOWN
Classifier: Topic :: Multimedia :: Video
Classifier: Development Status :: 4 - Beta
Classifier: Environment :: Console
Classifier: License :: OSI Approved :: Apache Software License
Classifier: Programming Language :: Python :: 2.6
Classifier: Programming Language :: Python :: 2.7
